[{"__type__":"cc.SpriteFrame","content":{"name":"icon_FTT","texture":"1f907dc9a","rect":[333,1640,100,35],"offset":[0,0],"originalSize":[100,35],"capInsets":[0,0,0,0]}},{"__type__":"cc.SpriteFrame","content":{"name":"icon_FTT_YELLOW","texture":"1f907dc9a","rect":[1569,1014,100,34],"offset":[0,0.5],"originalSize":[100,35],"capInsets":[0,0,0,0]}},{"__type__":"cc.SpriteFrame","content":{"name":"icon_FTT_RED","texture":"1f907dc9a","rect":[1569,1054,100,34],"offset":[0,0.5],"originalSize":[100,35],"capInsets":[0,0,0,0]}},{"__type__":"cc.SpriteFrame","content":{"name":"icon_FTT_FRAME","texture":"1f907dc9a","rect":[563,1639,100,35],"offset":[0,0],"originalSize":[100,35],"capInsets":[0,0,0,0]}},{"__type__":"cc.SpriteFrame","content":{"name":"icon_FTT_GREEN","texture":"1f907dc9a","rect":[1563,1094,100,34],"offset":[0,0.5],"originalSize":[100,35],"capInsets":[0,0,0,0]}}]